hmeter/__init__.py
hmeter/code.py
pathsolver/__init__.py
pathsolver/code.py
pathsolver-1.0.1.dist-info/LICENSE
pathsolver-1.0.1.dist-info/METADATA
pathsolver-1.0.1.dist-info/WHEEL
pathsolver-1.0.1.dist-info/top_level.txt
pathsolver-1.0.1.dist-info/RECORD
