Metadata-Version: 2.1
Name: pathsolver
Version: 1.0.1
Summary: A package to solve maze problem using A-star Algorithm.
Home-page: https://github.com/toshihiroryuu/
Author: Athul Mathew Konoor
Author-email: athulmathewkonoor@gmail.com
License: UNKNOWN
Platform: UNKNOWN
Classifier: Programming Language :: Python :: 3
Classifier: License :: OSI Approved :: MIT License
Classifier: Operating System :: OS Independent
Requires-Python: >=3.6
